paco.py
ipaco-0.0.0.dist-info/METADATA
ipaco-0.0.0.dist-info/WHEEL
ipaco-0.0.0.dist-info/top_level.txt
ipaco-0.0.0.dist-info/RECORD
